egse/tempcontrol/lakeshore/lakeshore336.py
egse/tempcontrol/lakeshore/lakeshore336.yaml
egse/tempcontrol/lakeshore/lakeshore336_cs.py
egse/tempcontrol/lakeshore/lakeshore336_devif.py
egse/tempcontrol/lakeshore/lakeshore336_protocol.py
lakeshore_tempcontrol/__init__.py
lakeshore_tempcontrol/cgse_explore.py
lakeshore_tempcontrol/cgse_services.py
lakeshore_tempcontrol/settings.yaml
lakeshore_tempcontrol-0.16.14.dist-info/METADATA
lakeshore_tempcontrol-0.16.14.dist-info/WHEEL
lakeshore_tempcontrol-0.16.14.dist-info/entry_points.txt
lakeshore_tempcontrol-0.16.14.dist-info/RECORD
